{
    "Q100887370": "EdyKusdaryanto",
    "Q100988130": "NaSulistyono",
    "Q102271998": "NicolasZurmendi",
    "Q1025215": "RossanaDeLosRios",
    "Q10320204": "LucasJovita",
    "Q103967160": "FredThome",
    "Q104049440": "AnselmoPuentes",
    "Q104180226": "CarlosChavez",
    "Q104247986": "RaulContreras",
    "Q104434382": "SochioKato",
    "Q104436023": "JunzoKawamori",
    "Q104783415": "ChantranithRos",
    "Q104833386": "EduardoAlvarez",
    "Q104840431": "RanXu",
    "Q106101619": "MikaBrunold",
    "Q106101651": "JanSebesta",
    "Q106102090": "LukaMikrut",
    "Q106102103": "DinoPrizmic",
    "Q106231271": "MilenaAvetisyan",
    "Q106351436": "AniSafaryan",
    "Q106351669": "LusineChobanyan",
    "Q106401426": "BornaDevald",
    "Q106401463": "AdrienGobat",
    "Q106510278": "KirillSinitsyn",
    "Q106988749": "LeonardoManta",
    "Q107214899": "NicoleRivkin",
    "Q107258170": "TomasLynch",
    "Q107455966": "OskarWikberg",
    "Q107484127": "EdasButvilas",
    "Q107581775": "AlessandroGravina",
    "Q107657048": "KeshavChopra",
    "Q108061473": "KylieBilchev",
    "Q108229030": "MatthewThomson",
    "Q108366310": "TamaraKostic",
    "Q108498952": "ColemanWong",
    "Q108550716": "ElaNalaMilic",
    "Q108599701": "DaniilOstapenkov",
    "Q108600827": "ViliusGaubas",
    "Q108760573": "SompornChampisri",
    "Q11409795": "NatsukiHarada",
    "Q11584907": "TomohiroIshii",
    "Q11718279": "JanLoth",
    "Q11828978": "PrzemyslawWarminski",
    "Q12022296": "JakubPraibis",
    "Q12275262": "VictorIvanchev",
    "Q12276263": "GeorgiArabov",
    "Q12287088": "MihailKanev",
    "Q12295327": "StefanTzvetkov",
    "Q12296173": "TeodorBachev",
    "Q12331658": "PeterMortensen",
    "Q12359554": "ArmandLevandi",
    "Q12362246": "ErikAunapuu",
    "Q1258713": "AstridSuurbeek",
    "Q1270395": "JoseLuisArilla",
    "Q1284978": "SamGroth",
    "Q12884739": "StefanosXydis",
    "Q13505930": "RolandasMuraska",
    "Q13512706": "MajaPalaversic",
    "Q13512890": "AurelKelemen",
    "Q13544": "CurtLincoln",
    "Q142744": "DomenicoVicini",
    "Q14657983": "MackenzieMcDonald",
    "Q1487851": "GaafarNoureldinElSadig",
    "Q14941252": "SujeongJang",
    "Q1505585": "GeorgPazderka",
    "Q1526170": "LudwigSalmHoogstraeten",
    "Q15696276": "GaborMathe",
    "Q15811879": "GerardBlasiFont",
    "Q15820541": "IvoSpathari",
    "Q15835459": "MohammedBouabdallah",
    "Q15836202": "NacirAbbes",
    "Q15847447": "SidAliAkili",
    "Q15996903": "WalterCrawley",
    "Q15997730": "GeorgeWrenn",
    "Q16006302": "CostasEfstratiadis",
    "Q16009346": "HenningMuller",
    "Q16029210": "AlbertLammens",
    "Q16063308": "BjornThalbitzer",
    "Q16065077": "PovlHenriksen",
    "Q16329088": "MaxBalli",
    "Q16474": "JohnMcEnroe",
    "Q16498105": "DartaElizabeteEmulina",
    "Q16533096": "ArturoSuque",
    "Q16546673": "RoosaTimonen",
    "Q16569512": "FredericoMarques",
    "Q16584907": "JuanManuelBlanc",
    "Q16728206": "KcCorkery",
    "Q16855281": "AllanMcDonald",
    "Q17059457": "ChristerFrancke",
    "Q1716927": "JurgSiegrist",
    "Q17305299": "FrancesTiafoe",
    "Q17438185": "ChristopherLewis",
    "Q17442289": "DavidSherbeck",
    "Q17660516": "TaylorFritz",
    "Q180535": "JuanMartindelPotro",
    "Q18544871": "RossWilliamGuignon",
    "Q18573478": "ThomasPichl",
    "Q18585183": "DarylMonfils",
    "Q18679123": "ChrisKermode",
    "Q18746244": "JeanClaudeGasigwa",
    "Q1895325": "FelixKaplan",
    "Q192661": "Jo-WilfriedTsonga",
    "Q193661": "StanWawrinka",
    "Q19520038": "SamThompson",
    "Q19668767": "WimFissette",
    "Q20056589": "FerruccioQuintavalle",
    "Q20085958": "KennyBun",
    "Q2040551": "TitoVazquez",
    "Q20740881": "DanielElahiGalan",
    "Q2081562": "LauraArraya",
    "Q21608193": "RupertWertheim",
    "Q22961763": "NurinNabilahRoslan",
    "Q23039257": "LloydHarris",
    "Q23039577": "JuanPabloVarillas",
    "Q23059683": "YusSyazlinNabilaBintiYusri",
    "Q2308951": "AnnGrossman",
    "Q23662473": "JoaoMenezes",
    "Q23759136": "JulienHoferlin",
    "Q23887617": "KhimIglupas",
    "Q24060952": "VasileiosIliopoulos",
    "Q24303923": "SefikFenmen",
    "Q24726725": "EricRoberson",
    "Q2479423": "WinnieShaw",
    "Q2553812": "GerardScheurleer",
    "Q25714023": "JurabekKarimov",
    "Q25756187": "PeterKhalil",
    "Q258930": "AsaCarlsson",
    "Q2593931": "TrudyGroenman",
    "Q25999553": "ShibuLal",
    "Q2624662": "RamonLaCroix",
    "Q2640230": "JanLehane",
    "Q26465813": "CarloBorea",
    "Q26799554": "J.J.Wolf",
    "Q26924391": "JuanCarlosAguilar",
    "Q27049217": "NoeliaZeballosMelgar",
    "Q27329680": "BramTenBerge",
    "Q27630156": "BojanBozovic",
    "Q28033759": "MarieMarechal",
    "Q28038578": "BoticvandeZandschulp",
    "Q28674037": "TomasBarriosVera",
    "Q28674131": "MohamedAzizDougaz",
    "Q28815635": "RyanThacher",
    "Q28839972": "FrancescMontanesRoca",
    "Q28842121": "ThassiloHaun",
    "Q299638": "HelenGourlay",
    "Q3021302": "DeidreCatt",
    "Q30301674": "BenPatael",
    "Q30327735": "NataliaBaudone",
    "Q30500142": "MarinosBaghdatis",
    "Q31088104": "LeonNorgarb",
    "Q31148006": "JenoPeteri",
    "Q3132631": "HenryBillington",
    "Q3142315": "HughStewart",
    "Q3162768": "JaroslavJust",
    "Q3168579": "JeanPaulLoth",
    "Q3178968": "JamesWillard",
    "Q3377586": "PetraLangrova",
    "Q3424732": "RicardoSaprissa",
    "Q3425309": "ReneSimpson",
    "Q3502012": "FrankoSkugor",
    "Q3507038": "LavrySylvainNyaba",
    "Q3617060": "AngeloMangiante",
    "Q3675645": "ChristianForcellini",
    "Q3854322": "AlexandarLazov",
    "Q39710308": "FehmiKizil",
    "Q40214925": "EvgeniiTiurnev",
    "Q40989587": "FrantisekSojka",
    "Q41855254": "KalmanKirchmayer",
    "Q4252035": "CristianGarin",
    "Q4665887": "AbdullaAlHaji",
    "Q46996397": "DudleyPitt",
    "Q47159169": "AnastasiaIamachkine",
    "Q47524103": "MarioKargl",
    "Q47524470": "AleksandrErnepesov",
    "Q4760148": "AndresArtunedoMartinavarro",
    "Q4762794": "AngelitaDetudamo",
    "Q4798960": "ArthurHam",
    "Q49562573": "AntoineHoang",
    "Q503310": "MaximeDecugis",
    "Q51151203": "SteveFurlong",
    "Q52063672": "PedroMartinez",
    "Q5246176": "DeanGoldfine",
    "Q5274812": "DiegoSchwartzman",
    "Q5295276": "DonaldWailanWalalangi",
    "Q53939648": "JoannaTomera",
    "Q5515629": "GabrielFrancini",
    "Q553457": "BobbyWilson",
    "Q55760933": "QiangHuaMeng",
    "Q569234": "AnnetteVanZyl",
    "Q6104711": "ReinhardtTrollip",
    "Q6114343": "JackFridtjofCharlesHaakeCoucheronNobelNielsen",
    "Q614675": "PatrickMcEnroe",
    "Q61670796": "MargaretaStrandberg",
    "Q6174310": "JeffLandau",
    "Q6230059": "AndreWall",
    "Q62554609": "FernandoGarciaLleo",
    "Q6286470": "JosephRahme",
    "Q6298741": "JuanSebastianVivanco",
    "Q63191311": "MalikaaMarathe",
    "Q63379052": "ArnarSigurdsson",
    "Q6339174": "CharlesWennergren",
    "Q63986039": "BirgerAndersenBrem",
    "Q64027661": "OysteinSteiro",
    "Q64212566": "PerErikKarlsson",
    "Q64392313": "LarsHjarrand",
    "Q64426765": "KjerstiJensen",
    "Q64748131": "KatarinaMarinkovikj",
    "Q65054681": "KyleJohnson",
    "Q6709499": "LynseyMccullough",
    "Q681398": "TatsuyoshiMiki",
    "Q6828749": "MichaelBoulding",
    "Q70463988": "InesBekrar",
    "Q7145979": "PatricioRodriguezChi",
    "Q7289587": "RaminRaziani",
    "Q7289650": "RamizAkhmerov",
    "Q7295107": "RasmusJonasson",
    "Q7660386": "SaeedMohammedHadi",
    "Q8017162": "WilliamQuillian",
    "Q84072816": "PeterHoll",
    "Q84322341": "IbianHodgson",
    "Q84350432": "AnchisaChanta",
    "Q87395391": "EduardoGorostiaga",
    "Q88134587": "MohammedArifElahi",
    "Q93134641": "RafaellaBaquerizo",
    "Q95218": "HansJurgenPohmann",
    "Q95452378": "OmarKa",
    "Q95999495": "JohanTheron",
    "Q96402451": "RogerPettersson",
    "Q96664315": "VictorLopezMoron",
    "Q96756015": "MariusLunde",
    "Q97148653": "RunarGranholm",
    "Q974176": "DanielMunozdelaNava",
    "Q98113952": "KhanIftikharAhmed",
    "Q98164050": "AyedZatar",
    "Q99527345": "TeddyTandjung",
    "Q99766997": "NoureddineMahmoudi"
}